cogscikit/__init__.py
cogscikit-0.1.0.dist-info/METADATA
cogscikit-0.1.0.dist-info/WHEEL
cogscikit-0.1.0.dist-info/top_level.txt
cogscikit-0.1.0.dist-info/RECORD
